chatgpt_block/__init__.py
chatgpt_block/chatgpt_block.py
chatgpt_block-0.1.6.dist-info/LICENSE
chatgpt_block-0.1.6.dist-info/METADATA
chatgpt_block-0.1.6.dist-info/WHEEL
chatgpt_block-0.1.6.dist-info/top_level.txt
chatgpt_block-0.1.6.dist-info/RECORD
