Metadata-Version: 2.1
Name: chatgpt-block
Version: 0.1.6
License-File: LICENSE
Requires-Dist: openai (>=0.27.2)
Requires-Dist: requests (>=2.28.2)
Requires-Dist: tiktoken (>=0.3.2)
